lclPyO3-1.0.0.dist-info/METADATA
lclPyO3-1.0.0.dist-info/WHEEL
lclPyO3-1.0.0.dist-info/license_files/LICENSE
lclPyO3/benchmark/statistics.py
lclPyO3/benchmark/__init__.py
lclPyO3/benchmark/benchmark.py
lclPyO3/aidfunc/error_func.py
lclPyO3/aidfunc/convert_data.py
lclPyO3/aidfunc/__init__.py
lclPyO3/aidfunc/logging.py
lclPyO3/aidfunc/add_to_data_func.py
lclPyO3/aidfunc/pass_func.py
lclPyO3/aidfunc/is_improvement_func.py
lclPyO3/problem/array_problem.py
lclPyO3/problem/abstract_local_search_problem.py
lclPyO3/problem/__init__.py
lclPyO3/localsearch/vns/__init__.py
lclPyO3/localsearch/vns/variable_neighbourhood.py
lclPyO3/localsearch/tabusearch/abstract_diff_state.py
lclPyO3/localsearch/tabusearch/tabu_search.py
lclPyO3/localsearch/tabusearch/__init__.py
lclPyO3/localsearch/tabusearch/sum_diff_state.py
lclPyO3/localsearch/tabusearch/tabu_list.py
lclPyO3/localsearch/simulatedannealing/abstr_iterations_temp_function.py
lclPyO3/localsearch/simulatedannealing/abstract_cooling_function.py
lclPyO3/localsearch/simulatedannealing/__init__.py
lclPyO3/localsearch/simulatedannealing/simulated_annealing.py
lclPyO3/localsearch/simulatedannealing/cnst_iterations_temp_function.py
lclPyO3/localsearch/simulatedannealing/geometric_cooling_function.py
lclPyO3/localsearch/steepestdescent/__init__.py
lclPyO3/localsearch/steepestdescent/steepest_descent.py
lclPyO3/localsearch/__init__.py
lclPyO3/localsearch/acceptance/abstract_acceptance_function.py
lclPyO3/localsearch/acceptance/__init__.py
lclPyO3/localsearch/acceptance/simulated_annealing_acceptance_function.py
lclPyO3/localsearch/abstract_local_search.py
lclPyO3/localsearch/move/array_swap.py
lclPyO3/localsearch/move/array_reverse_order.py
lclPyO3/localsearch/move/__init__.py
lclPyO3/localsearch/move/tsp_array_swap.py
lclPyO3/localsearch/move/multi_neighbourhood.py
lclPyO3/localsearch/move/abstract_move.py
lclPyO3/evaluation/deltaeval/delta_qap.py
lclPyO3/evaluation/deltaeval/__init__.py
lclPyO3/evaluation/deltaeval/delta_multi_neighbourhood.py
lclPyO3/evaluation/deltaeval/delta_tsp.py
lclPyO3/evaluation/deltaeval/delta_eval_func.py
lclPyO3-1.0.0.dist-info/RECORD
